bandits/__init__.py
bandits/beta_bandit.py
bandits/data_gen.py
bandits/plots.py
decision_engine-0.0.0b1.dist-info/LICENSE
decision_engine-0.0.0b1.dist-info/METADATA
decision_engine-0.0.0b1.dist-info/WHEEL
decision_engine-0.0.0b1.dist-info/top_level.txt
decision_engine-0.0.0b1.dist-info/RECORD
