Metadata-Version: 2.1
Name: decision-engine
Version: 0.0.0b1
Summary: Models for decision optimization and automation
Home-page: https://github.com/BellwethrInc/decision_engine
Author: Allen Grimm, Matt Moody, Jordan Roth
Author-email: 
License: UNKNOWN
Keywords: sample,setuptools,development
Platform: UNKNOWN
Classifier: Development Status :: 4 - Beta
Classifier: Programming Language :: Python :: 3
Classifier: License :: OSI Approved :: Apache Software License
Classifier: Operating System :: OS Independent
Requires-Python: >=3.6, <4
Requires-Dist: numpy
Requires-Dist: scipy
